pydatatracker/__init__.py
pydatatracker/_version.py
pydatatracker/config.py
pydatatracker/exporters.py
pydatatracker/observers.py
pydatatracker/types/_trackbase.py
pydatatracker/types/actor.py
pydatatracker/types/trackedattributes.py
pydatatracker/types/trackeddict.py
pydatatracker/types/trackedlist.py
pydatatracker/utils/__init__.py
pydatatracker/utils/changelog.py
pydatatracker-0.1.0.dist-info/METADATA
pydatatracker-0.1.0.dist-info/WHEEL
pydatatracker-0.1.0.dist-info/licenses/LICENSE
pydatatracker-0.1.0.dist-info/RECORD
