Metadata-Version: 2.4
Name: pydatatracker
Version: 0.1.0
Summary: Change-tracking containers for structured Python data
Project-URL: Homepage, https://github.com/your-org/pydatatracker
Project-URL: Repository, https://github.com/your-org/pydatatracker
Project-URL: Documentation, https://github.com/your-org/pydatatracker/tree/main/docs
Author: PyDataTracker Contributors
License: MIT License
License-File: LICENSE
Keywords: audit,containers,state,tracking
Classifier: Development Status :: 3 - Alpha
Classifier: Intended Audience :: Developers
Classifier: License :: OSI Approved :: MIT License
Classifier: Programming Language :: Python :: 3
Classifier: Programming Language :: Python :: 3.12
Classifier: Topic :: Software Development :: Libraries
Requires-Python: >=3.12
Provides-Extra: dev
Requires-Dist: pytest-cov>=5.0; extra == 'dev'
Requires-Dist: pytest>=8.3; extra == 'dev'
Requires-Dist: ruff>=0.5; extra == 'dev'
